django_lineup-1.0.0.dist-info/licenses/AUTHORS.rst
django_lineup-1.0.0.dist-info/licenses/LICENSE
lineup/__init__.py
lineup/admin.py
lineup/apps.py
lineup/exceptions.py
lineup/forms.py
lineup/managers.py
lineup/models.py
lineup/urls.py
lineup/views.py
lineup/management/commands/import_menu_from_json.py
lineup/migrations/0001_initial.py
lineup/migrations/__init__.py
lineup/static/css/lineup.css
lineup/static/js/lineup.js
lineup/templates/admin/lineup/menuitem/change_list.html
lineup/templates/lineup/base.html
lineup/templates/lineup/breadcrumbs.html
lineup/templates/lineup/menu.html
lineup/templatetags/lineup_tags.py
django_lineup-1.0.0.dist-info/METADATA
django_lineup-1.0.0.dist-info/WHEEL
django_lineup-1.0.0.dist-info/top_level.txt
django_lineup-1.0.0.dist-info/RECORD
