Metadata-Version: 2.4
Name: django-lineup
Version: 1.0.0
Summary: Navigation system for django sites
Home-page: https://github.com/otto-torino/django-lineup
Author: abidibo
Author-email: abidibo@gmail.com
License: MIT
Project-URL: Documentation, https://django-lineup.readthedocs.io/en/latest/
Project-URL: Source, https://github.com/otto-torino/django-lineup
Project-URL: Tracker, https://github.com/otto-torino/django-lineup/issues
Keywords: django-lineup
Classifier: Development Status :: 5 - Production/Stable
Classifier: Framework :: Django :: 2.1
Classifier: Intended Audience :: Developers
Classifier: License :: OSI Approved :: BSD License
Classifier: Natural Language :: English
Classifier: Programming Language :: Python :: 2
Classifier: Programming Language :: Python :: 2.7
Classifier: Programming Language :: Python :: 3
Classifier: Programming Language :: Python :: 3.5
Classifier: Programming Language :: Python :: 3.6
License-File: LICENSE
License-File: AUTHORS.rst
Requires-Dist: django-mptt
Dynamic: author
Dynamic: author-email
Dynamic: classifier
Dynamic: description
Dynamic: home-page
Dynamic: keywords
Dynamic: license
Dynamic: license-file
Dynamic: project-url
Dynamic: requires-dist
Dynamic: summary
